{
  "community": "alt-right",
  "scrubbing_strategy": "delete",
  "note": "0",

  "staining_videos": ["xuRfQFvhsds", "e7rBeM9tgpw", "JYvgvkKT0Ow", "O8sO86jRdOM", "J58gQXjXIEc", "PeQ9AyC--nM", "2M2dDLSroYw", "MJwncHyFsJo", "1VvZGNJGopM", "81tZeOCNf1A", "hCTBixmYlr0", "M-N6RmSLY0Q", "RHpalC3WaXY", "Ma5jjo714a0", "NLkFyhmt4vA", "n12xwL9fhng", "pojr13szcVA", "-pssDth__Rk", "r2T8akG6jGE", "oEUTSkobrE8", "swaMx0RhBsQ", "Q-K5tKOZWag", "onKUk1Yjt60", "6kJZeyL-jKI", "nd1pHD3uWPg", "BKfndD1ALSg", "wFxG-TStOnU", "M64e3ZfA2PI", "w3zFUZejKxM", "_R6eB_oSl-Y", "vVmIszHH7lo", "yov4FsRlgNQ", "YKjwYaOuAGA", "WTSDRo_m8U4", "8zXlkpS2340", "vTKXL_vBBBk", "b_KYJbjDWAs", "97lktPiWbeY", "mzxn34Kn8QQ", "XWJD7aFkbbQ"],
  "scrubbing_extras": [],

  "account_username": "Tandy.Dakota",
  "account_password": "scrub2022",
  "chrome_arguments": []
}
